{
  "id": "4482817",
  "name": "vue3-admin",
  "font_family": "iconfont",
  "css_prefix_text": "icon-",
  "description": "",
  "glyphs": [
    {
      "icon_id": "6486140",
      "name": "search",
      "font_class": "search",
      "unicode": "e64f",
      "unicode_decimal": 58959
    },
    {
      "icon_id": "1224913",
      "name": "download",
      "font_class": "download",
      "unicode": "e6a5",
      "unicode_decimal": 59045
    },
    {
      "icon_id": "8455373",
      "name": "验证码",
      "font_class": "yanzhengma",
      "unicode": "e619",
      "unicode_decimal": 58905
    },
    {
      "icon_id": "11372676",
      "name": "密码",
      "font_class": "mima",
      "unicode": "e8b2",
      "unicode_decimal": 59570
    },
    {
      "icon_id": "12704986",
      "name": "用户名",
      "font_class": "yonghuming",
      "unicode": "e60a",
      "unicode_decimal": 58890
    }
  ]
}
